trw/__init__.py
trw/metadata.py
trw/arch/__init__.py
trw/arch/darts_cell.py
trw/arch/darts_ops.py
trw/arch/darts_optimizer.py
trw/datasets/__init__.py
trw/datasets/chunked_dataset.py
trw/datasets/cifar10.py
trw/datasets/dataset_fake_symbols.py
trw/datasets/dataset_fake_symbols_2d.py
trw/datasets/dataset_fake_symbols_3d.py
trw/datasets/mnist.py
trw/datasets/utils.py
trw/datasets/voc2012.py
trw/hparams/__init__.py
trw/hparams/interpret_params.py
trw/hparams/params.py
trw/hparams/params_optimizer_hyperband.py
trw/hparams/params_optimizer_random_search.py
trw/layers/__init__.py
trw/layers/convs_2d.py
trw/layers/convs_3d.py
trw/layers/denses.py
trw/layers/flatten.py
trw/layers/shift_scale.py
trw/layers/unet_2d.py
trw/layers/utils.py
trw/simple_layers/__init__.py
trw/simple_layers/compiled_net.py
trw/simple_layers/convs.py
trw/simple_layers/denses.py
trw/simple_layers/global_pooling.py
trw/simple_layers/ordered_set.py
trw/simple_layers/shift_scale.py
trw/simple_layers/simple_layers.py
trw/simple_layers/simple_layers_implementations.py
trw/train/__init__.py
trw/train/analysis_plots.py
trw/train/callback.py
trw/train/callback_activation_statistics.py
trw/train/callback_data_summary.py
trw/train/callback_embedding_statistics.py
trw/train/callback_epoch_summary.py
trw/train/callback_explain_decision.py
trw/train/callback_export_augmentations.py
trw/train/callback_export_best_history.py
trw/train/callback_export_classification_errors.py
trw/train/callback_export_classification_report.py
trw/train/callback_export_convolution_kernel.py
trw/train/callback_export_history.py
trw/train/callback_export_samples.py
trw/train/callback_learning_rate_finder.py
trw/train/callback_learning_rate_recorder.py
trw/train/callback_model_summary.py
trw/train/callback_save_last_model.py
trw/train/callback_skip_epoch.py
trw/train/callback_tensorboard.py
trw/train/callback_tensorboard_embedding.py
trw/train/callback_tensorboard_record_history.py
trw/train/callback_tensorboard_record_model.py
trw-0.1.0.dist-info/LICENSE
trw-0.1.0.dist-info/METADATA
trw-0.1.0.dist-info/WHEEL
trw-0.1.0.dist-info/top_level.txt
trw-0.1.0.dist-info/RECORD
