Metadata-Version: 2.1
Name: trw
Version: 0.1.0
Summary: Train, test, debug and optimize PyTorch models
Home-page: https://github.com/civodlu/trw
Author: Civodlu
Author-email: civodlu@gmail.com
License: MIT
Download-URL: https://github.com/civodlu/trw/tarball/0.1.0
Platform: UNKNOWN
Classifier: Development Status :: 3 - Alpha
Classifier: Intended Audience :: Developers
Classifier: Programming Language :: Python :: 3
Requires-Dist: matplotlib
Requires-Dist: numpy
Requires-Dist: sklearn
Requires-Dist: scikit-image
Requires-Dist: pandas
Requires-Dist: tensorboardX
Requires-Dist: tensorboard
Requires-Dist: onnx
